<h:html xmlns="http://www.w3.org/2002/xforms"
        xmlns:h="http://www.w3.org/1999/xhtml"
        xmlns:ev="http://www.w3.org/2001/xml-events"
        xmlns:xsd="http://www.w3.org/2001/XMLSchema"
        xmlns:jr="http://openrosa.org/javarosa">
  <h:head>
    <h:title>Simple Example</h:title>

    <model>
      <instance>
        <faims id="simple_example">
          <style>
            <orientation>
                <orientation></orientation>
            </orientation>
            <even>
                <layout_weight></layout_weight>
            </even>
          </style>
          <user>
              <tab1>
                  <users></users>
              </tab1>
          </user>
          <menu>
              <tab1>
                <startsync/>
                <stopsync/>
                <options></options>
              </tab1>
          </menu>
          <tabgroup1>
              <tab1>
                  <name></name>
                  <description></description>
                  <value></value>
                  <timestamp></timestamp>
                  <date></date>
                  <time></time>
                  <location></location>
                  <choice></choice>
                  <item></item>
                  <type></type>
                  <gallery></gallery>
                  <rocks></rocks>
                  <files></files>
                  <attachfile></attachfile>
                  <pictures></pictures>
                  <attachpicture></attachpicture>
                  <videos></videos>
                  <attachvideo></attachvideo>
                  <audios></audios>
                  <attachaudio></attachaudio>
                  <viewattached></viewattached>
                   <scvalue></scvalue>
                  <scancode></scancode>
                  <container>
                      <save></save>
                      <clear></clear>
                  </container>
                  <delete></delete>
                  <close></close>
              </tab1>
              <tab2>
                  <entities></entities>
                  <load></load>
              </tab2>
          </tabgroup1>
          <tabgroup3>
              <tab1>
                  <container>
	                  <name></name>
	                  <description></description>
	                  <value></value>
	                  <timestamp></timestamp>
	                  <date></date>
                 	  <time></time>
	                  <location></location>
	                  <choice></choice>
	                  <item></item>
	                  <type></type>
	                  <gallery></gallery>
	                  <rocks></rocks>
	                  <files></files>
	                  <attachfile></attachfile>
	                  <pictures></pictures>
	                  <attachpicture></attachpicture>
	                  <videos></videos>
	                  <attachvideo></attachvideo>
	                  <audios></audios>
	                  <attachaudio></attachaudio>
	                  <viewattached></viewattached>
	                  <container1>
	                      <save></save>
	                      <clear></clear>
	                  </container1>
	                  <delete></delete>
	                  <close></close>
	          	</container>
              </tab1>
              <tab2>
                  <entities></entities>
                  <load></load>
              </tab2>
          </tabgroup3>
          <tabgroup5>
              <tab1>
                  <name></name>
                  <description></description>
                  <value></value>
                  <timestamp></timestamp>
                  <date></date>
                  <time></time>
                  <location></location>
                  <choice></choice>
                  <item></item>
                  <type></type>
                  <gallery></gallery>
                  <rocks></rocks>
                  <files></files>
                  <attachfile></attachfile>
                  <pictures></pictures>
                  <attachpicture></attachpicture>
                  <videos></videos>
                  <attachvideo></attachvideo>
                  <audios></audios>
                  <attachaudio></attachaudio>
                  <viewattached></viewattached>
                   <clear></clear>
                  <delete></delete>
                  <close></close>
              </tab1>
              <tab2>
                  <entities></entities>
                  <load></load>
              </tab2>
          </tabgroup5>
          <tabgroup7>
              <tab1>
                  <entity1/>
                  <entity2/>
                  <verb></verb>
                  <add></add>
              </tab1>
          </tabgroup7>
          <tabgroup8>
              <tab1>
                  <queries></queries>
                  <load></load>
                  <table></table>
                  <container>
                      <child1>
                      	<top></top>
                      </child1>
                      <child2>
                      	<bottom></bottom>
                      </child2>
                      <child3>
                      	<scrollRow></scrollRow>
                      </child3>
                      <child4>
                      	<row></row>
                      </child4>
                  </container>
              </tab1>
          </tabgroup8>
        </faims>
      </instance>
      
      <bind nodeset="/faims/tabgroup1/tab1/description" type="string"/>
      <bind nodeset="/faims/tabgroup1/tab1/value" type="decimal"/>
      <bind nodeset="/faims/tabgroup1/tab1/date" type="date"/>
      <bind nodeset="/faims/tabgroup1/tab1/time" type="time"/>
      <bind nodeset="/faims/tabgroup3/tab1/container/description" type="string"/>
      <bind nodeset="/faims/tabgroup3/tab1/container/value" type="decimal"/>
      <bind nodeset="/faims/tabgroup3/tab1/container/date" type="date"/>
      <bind nodeset="/faims/tabgroup3/tab1/container/time" type="time"/>
      <bind nodeset="/faims/tabgroup5/tab1/description" type="string"/>
      <bind nodeset="/faims/tabgroup5/tab1/value" type="decimal"/>
      <bind nodeset="/faims/tabgroup5/tab1/date" type="date"/>
      <bind nodeset="/faims/tabgroup5/tab1/time" type="time"/>
      <bind nodeset="/faims/tabgroup8/tab1/container/child3/scrollRow" type="decimal"/>
      
    </model>
  </h:head>

  
  <h:body>
    <group ref="style">
      <label></label>
      <group ref="orientation">
        <label></label>
        <input ref="orientation">
            <label>horizontal</label>
        </input>
      </group>
      <group ref="even">
        <label></label>
        <input ref="layout_weight">
            <label>1</label>
        </input>
      </group>
    </group>
    <group ref="user">
      <label>Users List</label>
      <group ref="tab1" faims_scrollable="false">
        <label>User List</label>
        <select1 ref="users" appearance="compact">
          <label>Users:</label>
          <item>
            <label>dummy</label>
            <value>dummy</value>
          </item>
        </select1>
      </group>
    </group>
    <group ref="menu">
      <label>Options</label>
      <group ref="tab1" faims_scrollable="false">
        <label>Options</label>
        <trigger ref="startsync">
          <label>Start Syncing</label>
        </trigger>
        <trigger ref="stopsync">
          <label>Stop Syncing</label>
        </trigger>
        <select1 ref="options" appearance="compact">
          <label>Options:</label>
          <item>
            <label>dummy</label>
            <value>dummy</value>
          </item>
        </select1>

      </group>
    </group>
    <group ref="tabgroup1" faims_archent_type="small">
      <label>Entity</label>
      <group ref="tab1" faims_hidden="false">
        <label>Save Entity</label>
	        <input ref="name" faims_attribute_name="name" faims_attribute_type="measure">
	          	<label>Name:</label>
	        </input>
	        <input ref="description" faims_attribute_name="description" faims_attribute_type="measure">
	          	<label>Description:</label>
	        </input>
	        <input ref="value" faims_attribute_name="value" faims_attribute_type="measure">
	            <label>Value:</label>
	        </input>
	        <input ref="timestamp" faims_attribute_name="timestamp" faims_attribute_type="measure" faims_read_only="true" faims_certainty="false">
              <label>Timestamp:</label>
            </input>
            <input ref="date" faims_attribute_name="date" faims_attribute_type="measure">
            	<label>Date:</label>
         	</input>
         	<input ref="time" faims_attribute_name="time" faims_attribute_type="measure">
            	<label>Time:</label>
         	</input>
            <select ref="location" faims_attribute_name="location" faims_attribute_type="vocab">
                <label>Location:</label>
                <item>
                	<label>dummy</label>
                	<value>dummy</value>
              	</item>
            </select>
             <select1 ref="choice" appearance="full" faims_attribute_name="choice" faims_attribute_type="vocab">
	            <label>Choice:</label>
	            <item>
	            	<label>dummy</label>
	            	<value>dummy</value>
	          	</item>
	        </select1>
	        <select1 ref="item" faims_attribute_name="item" faims_attribute_type="vocab">
	            <label>Item:</label>
	            <item>
	            	<label>dummy</label>
	            	<value>dummy</value>
	          	</item>
	        </select1>
	        <select1 ref="type" faims_attribute_name="type" faims_attribute_type="vocab">
	            <label>Type:</label>
	            <item>
	            	<label>dummy</label>
	            	<value>dummy</value>
	          	</item>
	        </select1>
	        <select1 ref="gallery" type="image" faims_attribute_name="gallery" faims_attribute_type="vocab">
	            <label>Gallery:</label>
	            <item>
	                <label>dummy</label>
	                <value>dummy</value>
	            </item>
	        </select1>
	        <select1 ref="rocks" type="image" faims_attribute_name="rocks" faims_attribute_type="vocab">
	            <label>Rocks:</label>
	            <item>
	                <label>dummy</label>
	                <value>dummy</value>
	            </item>
	        </select1>
	        <select ref="files" type="file" faims_attribute_name="file" faims_attribute_type="measure" faims_annotation="true" faims_certainty="true">
	            <label>Files:</label>
	            <item>
	                <label>dummy</label>
	                <value>dummy</value>
	            </item>
	        </select>
	        <trigger ref="attachfile">
	            <label>Attached File:</label>
	        </trigger>
	        <select ref="pictures" type="camera" faims_sync="true" faims_attribute_name="picture" faims_attribute_type="measure" faims_annotation="true" faims_certainty="true">
	            <label>Pictures:</label>
	            <item>
	                <label>dummy</label>
	                <value>dummy</value>
	            </item>
	        </select>
	        <trigger ref="attachpicture">
	            <label>Take picture</label>
	        </trigger>
	        <select ref="videos" type="video" faims_attribute_name="video" faims_attribute_type="measure" faims_annotation="true" faims_certainty="true">
	            <label>Videos:</label>
	            <item>
	                <label>dummy</label>
	                <value>dummy</value>
	            </item>
	        </select>
	        <trigger ref="attachvideo">
	            <label>Take video</label>
	        </trigger>
	        <select ref="audios" type="file" faims_attribute_name="audio" faims_attribute_type="measure" faims_annotation="true" faims_certainty="true">
	            <label>Audios:</label>
	            <item>
	                <label>dummy</label>
	                <value>dummy</value>
	            </item>
	        </select>
	        <trigger ref="attachaudio">
	            <label>Record Audio</label>
	        </trigger>
	        <trigger ref="viewattached">
	            <label>View Attached Files</label>
	        </trigger>
	         <input ref="scvalue" faims_attribute_name="scvalue" faims_attribute_type="measure">
	          	<label>Scan Code Text:</label>
	        </input>
	        <trigger ref="scancode">
              <label>Scan Code</label>
          </trigger>
	        <group ref="container" faims_style="orientation even">
	          <label></label>
	            <trigger ref="save">
	              <label>Save</label>
	            </trigger>
	            <trigger ref="clear">
	              <label>Clear</label>
	            </trigger>
	        </group>
	        <trigger ref="delete">
	          <label>Delete</label>
	        </trigger>
	        <trigger ref="close">
	          <label>Close</label>
	        </trigger>
      </group>
      <group ref="tab2" faims_scrollable="false">
        <label>Load Entity</label>
       	<select1 ref="entities" appearance="compact">
            <label>Entity:</label>
            <item>
            	<label>dummy</label>
            	<value>dummy</value>
          	</item>
        </select1>
      </group>
    </group>
    <group ref="tabgroup3" faims_archent_type="small">
      <label>Entity</label>
      <group ref="tab1" faims_hidden="false">
        <label>Save Entity</label>
        	<group ref="container">
        	    <label></label>
	        <input ref="name" faims_attribute_name="name" faims_attribute_type="measure">
	          	<label>Name:</label>
	        </input>
	        <input ref="description" faims_attribute_name="description" faims_attribute_type="measure">
	          	<label>Description:</label>
	        </input>
	        <input ref="value" faims_attribute_name="value" faims_attribute_type="measure">
	            <label>Value:</label>
	        </input>
	        <input ref="timestamp" faims_attribute_name="timestamp" faims_attribute_type="measure" faims_read_only="true" faims_certainty="false">
              <label>Timestamp:</label>
            </input>
            <input ref="date" faims_attribute_name="date" faims_attribute_type="measure">
            	<label>Date:</label>
         	</input>
         	<input ref="time" faims_attribute_name="time" faims_attribute_type="measure">
            	<label>Time:</label>
         	</input>
            <select ref="location" faims_attribute_name="location" faims_attribute_type="vocab">
                <label>Location:</label>
                <item>
                	<label>dummy</label>
                	<value>dummy</value>
              	</item>
            </select>
             <select1 ref="choice" appearance="full" faims_attribute_name="choice" faims_attribute_type="vocab">
	            <label>Choice:</label>
	            <item>
	            	<label>dummy</label>
	            	<value>dummy</value>
	          	</item>
	        </select1>
	        <select1 ref="item" faims_attribute_name="item" faims_attribute_type="vocab">
	            <label>Item:</label>
	            <item>
	            	<label>dummy</label>
	            	<value>dummy</value>
	          	</item>
	        </select1>
	        <select1 ref="type" faims_attribute_name="type" faims_attribute_type="vocab">
	            <label>Type:</label>
	            <item>
	            	<label>dummy</label>
	            	<value>dummy</value>
	          	</item>
	        </select1>
	        <select1 ref="gallery" type="image" faims_attribute_name="gallery" faims_attribute_type="vocab">
	            <label>Gallery:</label>
	            <item>
	                <label>dummy</label>
	                <value>dummy</value>
	            </item>
	        </select1>
	        <select1 ref="rocks" type="image" faims_attribute_name="rocks" faims_attribute_type="vocab">
	            <label>Rocks:</label>
	            <item>
	                <label>dummy</label>
	                <value>dummy</value>
	            </item>
	        </select1>
	        <select ref="files" type="file" faims_attribute_name="file" faims_attribute_type="measure" faims_annotation="true" faims_certainty="true">
	            <label>Files:</label>
	            <item>
	                <label>dummy</label>
	                <value>dummy</value>
	            </item>
	        </select>
	        <trigger ref="attachfile">
	            <label>Attached File:</label>
	        </trigger>
	        <select ref="pictures" type="camera" faims_sync="true" faims_attribute_name="picture" faims_attribute_type="measure" faims_annotation="true" faims_certainty="true">
	            <label>Pictures:</label>
	            <item>
	                <label>dummy</label>
	                <value>dummy</value>
	            </item>
	        </select>
	        <trigger ref="attachpicture">
	            <label>Take picture</label>
	        </trigger>
	        <select ref="videos" type="video" faims_attribute_name="video" faims_attribute_type="measure" faims_annotation="true" faims_certainty="true">
	            <label>Videos:</label>
	            <item>
	                <label>dummy</label>
	                <value>dummy</value>
	            </item>
	        </select>
	        <trigger ref="attachvideo">
	            <label>Take video</label>
	        </trigger>
	        <select ref="audios" type="file" faims_attribute_name="audio" faims_attribute_type="measure" faims_annotation="true" faims_certainty="true">
	            <label>Audios:</label>
	            <item>
	                <label>dummy</label>
	                <value>dummy</value>
	            </item>
	        </select>
	        <trigger ref="attachaudio">
	            <label>Record Audio</label>
	        </trigger>
	        <trigger ref="viewattached">
	            <label>View Attached Files</label>
	        </trigger>
	        <group ref="container1" faims_style="orientation even">
	          <label></label>
	            <trigger ref="save">
	              <label>Save</label>
	            </trigger>
	            <trigger ref="clear">
	              <label>Clear</label>
	            </trigger>
	        </group>
	        <trigger ref="delete">
	          <label>Delete</label>
	        </trigger>
	        <trigger ref="close">
	          <label>Close</label>
	        </trigger>
	        </group>
      </group>
      <group ref="tab2" faims_scrollable="false">
        <label>Load Entity</label>
        <select1 ref="entities" appearance="compact">
            <label>Entity:</label>
            <item>
              <label>dummy</label>
              <value>dummy</value>
            </item>
        </select1>
      </group>
    </group>
    <group ref="tabgroup5" faims_archent_type="small">
      <label>Entity</label>
      <group ref="tab1" faims_hidden="false">
        <label>Save Entity</label>
	        <input ref="name" faims_attribute_name="name" faims_attribute_type="measure">
	          	<label>Name:</label>
	        </input>
	        <input ref="description" faims_attribute_name="description" faims_attribute_type="measure">
	          	<label>Description:</label>
	        </input>
	        <input ref="value" faims_attribute_name="value" faims_attribute_type="measure">
	            <label>Value:</label>
	        </input>
	        <input ref="timestamp" faims_attribute_name="timestamp" faims_attribute_type="measure" faims_read_only="true" faims_certainty="false">
              <label>Timestamp:</label>
            </input>
            <input ref="date" faims_attribute_name="date" faims_attribute_type="measure">
            	<label>Date:</label>
         	</input>
         	<input ref="time" faims_attribute_name="time" faims_attribute_type="measure">
            	<label>Time:</label>
         	</input>
            <select ref="location" faims_attribute_name="location" faims_attribute_type="vocab">
                <label>Location:</label>
                <item>
                	<label>dummy</label>
                	<value>dummy</value>
              	</item>
            </select>
             <select1 ref="choice" appearance="full" faims_attribute_name="choice" faims_attribute_type="vocab">
	            <label>Choice:</label>
	            <item>
	            	<label>dummy</label>
	            	<value>dummy</value>
	          	</item>
	        </select1>
	        <select1 ref="item" faims_attribute_name="item" faims_attribute_type="vocab">
	            <label>Item:</label>
	            <item>
	            	<label>dummy</label>
	            	<value>dummy</value>
	          	</item>
	        </select1>
	        <select1 ref="type" faims_attribute_name="type" faims_attribute_type="vocab">
	            <label>Type:</label>
	            <item>
	            	<label>dummy</label>
	            	<value>dummy</value>
	          	</item>
	        </select1>
	        <select1 ref="gallery" type="image" faims_attribute_name="gallery" faims_attribute_type="vocab">
	            <label>Gallery:</label>
	            <item>
	                <label>dummy</label>
	                <value>dummy</value>
	            </item>
	        </select1>
	        <select1 ref="rocks" type="image" faims_attribute_name="rocks" faims_attribute_type="vocab">
	            <label>Rocks:</label>
	            <item>
	                <label>dummy</label>
	                <value>dummy</value>
	            </item>
	        </select1>
	        <select ref="files" type="file" faims_attribute_name="file" faims_attribute_type="measure" faims_annotation="true" faims_certainty="true">
	            <label>Files:</label>
	            <item>
	                <label>dummy</label>
	                <value>dummy</value>
	            </item>
	        </select>
	        <trigger ref="attachfile">
	            <label>Attached File:</label>
	        </trigger>
	        <select ref="pictures" type="camera" faims_sync="true" faims_attribute_name="picture" faims_attribute_type="measure" faims_annotation="true" faims_certainty="true">
	            <label>Pictures:</label>
	            <item>
	                <label>dummy</label>
	                <value>dummy</value>
	            </item>
	        </select>
	        <trigger ref="attachpicture">
	            <label>Take picture</label>
	        </trigger>
	        <select ref="videos" type="video" faims_attribute_name="video" faims_attribute_type="measure" faims_annotation="true" faims_certainty="true">
	            <label>Videos:</label>
	            <item>
	                <label>dummy</label>
	                <value>dummy</value>
	            </item>
	        </select>
	        <trigger ref="attachvideo">
	            <label>Take video</label>
	        </trigger>
	        <select ref="audios" type="file" faims_attribute_name="audio" faims_attribute_type="measure" faims_annotation="true" faims_certainty="true">
	            <label>Audios:</label>
	            <item>
	                <label>dummy</label>
	                <value>dummy</value>
	            </item>
	        </select>
	        <trigger ref="attachaudio">
	            <label>Record Audio</label>
	        </trigger>
	        <trigger ref="viewattached">
	            <label>View Attached Files</label>
	        </trigger>
	        <trigger ref="clear">
	            <label>Clear</label>
	        </trigger>
	        <trigger ref="delete">
	          <label>Delete</label>
	        </trigger>
	        <trigger ref="close">
	          <label>Close</label>
	        </trigger>
      </group>
      <group ref="tab2" faims_scrollable="false">
        <label>Load Entity</label>
        <select1 ref="entities" appearance="compact">
            <label>Entity:</label>
            <item>
              <label>dummy</label>
              <value>dummy</value>
            </item>
        </select1>
      </group>
    </group>
    <group ref="tabgroup7">
        <label>Associations</label>
        <group ref="tab1">
            <label>Add Entity Member</label>
            <select1 ref="entity1">
                <label>Entity 1</label>
                <item>
	            	<label>dummy</label>
	            	<value>dummy</value>
	          	</item>
            </select1>
            <select1 ref="entity2">
                <label>Entity 2</label>
                <item>
	            	<label>dummy</label>
	            	<value>dummy</value>
	          	</item>
            </select1>
            <input ref="verb">
                <label>Verb</label>
            </input>
            <trigger ref="add">
              <label>Add member</label>
          	</trigger>
        </group>
    </group>
    <group ref="tabgroup8">
      <label>Table View</label>
      <group ref="tab1" faims_scrollable="false">
        <label>Table View</label>
        <select1 ref="queries">
            <label>Queries</label>
            <item>
	         	<label>dummy</label>
	         	<value>dummy</value>
	       	</item>
        </select1>
        <trigger ref="load">
        	<label>Load Query</label>
       	</trigger>
       	<input ref="table" faims_table="true">
        	<label></label>
       	</input>
       	<group ref="container" faims_style="orientation">
        	<label></label>
	        <group ref="child1" faims_style="even">
	        	<label></label>
	            <trigger ref="top">
	              <label>Top</label>
	            </trigger>
	        </group>
	        <group ref="child2" faims_style="even">
	        	<label></label>
	            <trigger ref="bottom">
	              <label>Bottom</label>
	            </trigger>
	        </group>
	        <group ref="child3" faims_style="even">
	        	<label></label>
	            <input ref="scrollRow">
	                <label>Scroll Row:</label>
	            </input>
	        </group>
	        <group ref="child4" faims_style="even">
	        	<label></label>
	            <trigger ref="row">
	              <label>Row</label>
	            </trigger>
	        </group>
	    </group>
      </group>
    </group>
  </h:body>
</h:html>
